rbIotModem/__init__.py
rbIotModem/_rbIotModem.so
rbIotModem/rbIotModem.py
rbIotModem-1.3.1.dist-info/METADATA
rbIotModem-1.3.1.dist-info/WHEEL
rbIotModem-1.3.1.dist-info/top_level.txt
rbIotModem-1.3.1.dist-info/RECORD
