Metadata-Version: 2.1
Name: rbIotModem
Version: 1.3.1
Summary: Ringbeller IoT Modem Library
Home-page: UNKNOWN
Author: Jeevan Anga @jeevan900929
Author-email: jeevan.900929@gmail.com
License: UNKNOWN
Platform: UNKNOWN
Classifier: Intended Audience :: Developers
Classifier: License :: OSI Approved :: MIT License
Classifier: Programming Language :: Python :: 3
Classifier: Programming Language :: Python :: 3.7
Classifier: Programming Language :: Python :: 3 :: Only
Requires-Python: >=3.7, <4
Requires-Dist: rx
Requires-Dist: prompt-toolkit
Requires-Dist: simple-chalk
Requires-Dist: inputimeout
Requires-Dist: click
